piger/__init__.py
piger/imageresize.py
piger/timecost.py
piger-0.1.1.dist-info/METADATA
piger-0.1.1.dist-info/RECORD
piger-0.1.1.dist-info/WHEEL
piger-0.1.1.dist-info/top_level.txt
