Metadata-Version: 2.1
Name: piger
Version: 0.1.1
Summary: 猪猪的wheel
Home-page: https://gitee.com/pigbrother_1/pig
Author: pigbrother
Author-email: 2751054328@qq.com
License: UNKNOWN
Platform: UNKNOWN
Classifier: Programming Language :: Python :: 3
Classifier: License :: OSI Approved :: MIT License
Classifier: Operating System :: OS Independent
